doveseed/__init__.py
doveseed/app.py
doveseed/cli.py
doveseed/config.py
doveseed/confirmation.py
doveseed/domain_types.py
doveseed/email_notification.py
doveseed/email_templating.py
doveseed/feed.py
doveseed/notifier.py
doveseed/recaptcha.py
doveseed/registration.py
doveseed/smtp.py
doveseed/storage.py
doveseed/token_gen.py
doveseed-2.1.3.dist-info/LICENSE
doveseed-2.1.3.dist-info/METADATA
doveseed-2.1.3.dist-info/WHEEL
doveseed-2.1.3.dist-info/RECORD
