Metadata-Version: 2.1
Name: doveseed
Version: 2.1.3
Summary: Doveseed is a backend service for email subscriptions to RSS feeds.
Home-page: https://github.com/jgosmann/doveseed/
License: MIT
Keywords: email,rss,subscriptions
Author: Jan Gosmann
Author-email: jan@hyper-world.de
Requires-Python: >=3.9.0,<4.0.0
Classifier: Development Status :: 5 - Production/Stable
Classifier: Framework :: Flask
Classifier: Intended Audience :: Developers
Classifier: License :: OSI Approved :: MIT License
Classifier: Programming Language :: Python :: 3
Classifier: Programming Language :: Python :: 3.9
Classifier: Programming Language :: Python :: 3.10
Classifier: Programming Language :: Python :: 3.11
Classifier: Programming Language :: Python :: 3.12
Classifier: Programming Language :: Python :: 3.13
Classifier: Programming Language :: Python :: 3 :: Only
Classifier: Topic :: Communications :: Email
Classifier: Topic :: Internet :: WWW/HTTP :: WSGI :: Application
Provides-Extra: all
Provides-Extra: recaptcha
Requires-Dist: aiohttp (>=3.8.4,<4.0.0) ; extra == "all" or extra == "recaptcha"
Requires-Dist: fastapi (>=0.115.3,<0.116.0)
Requires-Dist: jinja2 (>=3.1.2,<4.0.0)
Requires-Dist: pydantic-settings (>=2.2.0,<3.0.0)
Requires-Dist: starlette (>=0.41.2,<0.42.0) ; extra == "all" or extra == "recaptcha"
Requires-Dist: tinydb (>=4.7.0,<5.0.0)
Requires-Dist: typing_extensions (>=4.3.0,<5.0.0)
Project-URL: Repository, https://github.com/jgosmann/doveseed/
